MANIFEST.in
README.md
setup.py
dbt/adapters/__init__.py
dbt/adapters/greenplum/__init__.py
dbt/adapters/greenplum/__version__.py
dbt/adapters/greenplum/connections.py
dbt/adapters/greenplum/impl.py
dbt/include/greenplum/__init__.py
dbt/include/greenplum/dbt_project.yml
dbt/include/greenplum/sample_profiles.yml
dbt/include/greenplum/macros/adapters.sql
dbt/include/greenplum/macros/catalog.sql
dbt/include/greenplum/macros/distribution.sql
dbt/include/greenplum/macros/partitions.sql
dbt/include/greenplum/macros/storage_parameters.sql
dbt/include/greenplum/macros/materializations/snapshot_merge.sql
dbt_greenplum.egg-info/PKG-INFO
dbt_greenplum.egg-info/SOURCES.txt
dbt_greenplum.egg-info/dependency_links.txt
dbt_greenplum.egg-info/not-zip-safe
dbt_greenplum.egg-info/requires.txt
dbt_greenplum.egg-info/top_level.txt