Metadata-Version: 2.1
Name: dbt-greenplum
Version: 1.4.0
Summary: The greenplum adapter plugin for dbt (data build tool)
Home-page: https://github.com/markporoshin/dbt-greenplum
Author: Mark Poroshin
Author-email: mark.poroshin@yandex.ru
License: UNKNOWN
Platform: UNKNOWN
Classifier: Development Status :: 5 - Production/Stable
Classifier: License :: OSI Approved :: Apache Software License
Classifier: Operating System :: Microsoft :: Windows
Classifier: Operating System :: MacOS :: MacOS X
Classifier: Operating System :: POSIX :: Linux
Classifier: Programming Language :: Python :: 3.7
Classifier: Programming Language :: Python :: 3.8
Classifier: Programming Language :: Python :: 3.9
Classifier: Programming Language :: Python :: 3.10
Classifier: Programming Language :: Python :: 3.11
Requires-Python: >=3.7
